<annotation>
	<folder>my-project-name</folder>
	<filename>438c650ba0119366bfd73bc58a87215c0c45e03b.jpg</filename>
	<path>/my-project-name/438c650ba0119366bfd73bc58a87215c0c45e03b.jpg</path>
	<source>
		<database>Unspecified</database>
	</source>
	<size>
		<width>1773</width>
		<height>2364</height>
		<depth>3</depth>
	</size>
	<object>
		<name>Banner</name>
		<pose>Unspecified</pose>
		<truncated>0</truncated>
		<difficult>0</difficult>
		<bndbox>
			<xmin>347</xmin>
			<ymin>284</ymin>
			<xmax>461</xmax>
			<ymax>714</ymax>
		</bndbox>
	</object>
</annotation>